pipe_nonblock/__init__.py
pipe_nonblock/calls.py
pipe_nonblock/pipe.py
pipe_nonblock-0.4.dist-info/LICENSE.md
pipe_nonblock-0.4.dist-info/METADATA
pipe_nonblock-0.4.dist-info/WHEEL
pipe_nonblock-0.4.dist-info/top_level.txt
pipe_nonblock-0.4.dist-info/RECORD
