Metadata-Version: 2.1
Name: pipe-nonblock
Version: 0.4
Summary: Non-blocking multiprocessing pipe
Home-page: https://github.com/maxtwen/pipe-nonblock
Author: Maksim Afanasevsky
Author-email: maxtwen1@gmail.com
License: UNKNOWN
Download-URL: https://github.com/maxtwen/pipe-nonblock
Platform: UNKNOWN
